MANIFEST.in
README.rst
setup.cfg
setup.py
euroblock/__init__.py
euroblock/apps.py
euroblock/static/css/euroblock.css
euroblock/static/image/ajax_loader_metal_512.gif
euroblock/static/js/euroblock.js
euroblock/static/js/jquery.blockUI.js
eurocharts/__init__.py
eurocharts/apps.py
eurocharts/static/js/eurochart.js
eurocharts/static/lib/index.htm
eurocharts/static/lib/api/highmaps.html
eurocharts/static/lib/api/css/api.css
eurocharts/static/lib/api/css/font-awesome.min.css
eurocharts/static/lib/api/css/jquery-ui.min.css
eurocharts/static/lib/api/css/jquery.sidr.bare.css
eurocharts/static/lib/api/css/images/ui-bg_flat_75_ffffff_40x100.png
eurocharts/static/lib/api/css/images/ui-bg_glass_75_dadada_1x400.png
eurocharts/static/lib/api/fonts/fontawesome-webfont.woff
eurocharts/static/lib/api/fonts/fontawesome-webfont.woff2
eurocharts/static/lib/api/images/Highmaps.svg
eurocharts/static/lib/api/images/apple-touch-icon-114x114.png
eurocharts/static/lib/api/images/apple-touch-icon-120x120.png
eurocharts/static/lib/api/images/apple-touch-icon-144x144.png
eurocharts/static/lib/api/images/apple-touch-icon-152x152.png
eurocharts/static/lib/api/images/apple-touch-icon-180x180.png
eurocharts/static/lib/api/images/apple-touch-icon-57x57.png
eurocharts/static/lib/api/images/apple-touch-icon-60x60.png
eurocharts/static/lib/api/images/apple-touch-icon-72x72.png
eurocharts/static/lib/api/images/apple-touch-icon-76x76.png
eurocharts/static/lib/api/images/favicon-160x160.png
eurocharts/static/lib/api/images/favicon-16x16.png
eurocharts/static/lib/api/images/favicon-192x192.png
eurocharts/static/lib/api/images/favicon-32x32.png
eurocharts/static/lib/api/images/favicon-96x96.png
eurocharts/static/lib/api/images/sprite.png
eurocharts/static/lib/api/js/api.js
eurocharts/static/lib/api/js/highmaps.json
eurocharts/static/lib/api/js/jquery-1.11.3.min.js
eurocharts/static/lib/api/js/jquery-ui.min.js
eurocharts/static/lib/api/js/jquery.sidr.min.js
eurocharts/static/lib/examples/rich-info/index.htm
eurotools.egg-info/PKG-INFO
eurotools.egg-info/SOURCES.txt
eurotools.egg-info/dependency_links.txt
eurotools.egg-info/requires.txt
eurotools.egg-info/top_level.txt