Metadata-Version: 1.0
Name: eurotools
Version: 0.5.2
Summary: UNKNOWN
Home-page: http://www.stoneworksolutions.net
Author: Antonio Palomo Cardenas
Author-email: antonio.palomo@stoneworksolutions.net
License: UNKNOWN
Platform: UNKNOWN
